saitech_wapp-0.2.11.dist-info/licenses/LICENSE
wapp/__init__.py
wapp/cli.py
wapp/cli_commands/__init__.py
wapp/cli_commands/export.py
wapp/cli_commands/init.py
wapp/core/__init__.py
wapp/core/asgi.py
wapp/templates/__init__.py
wapp/templates/app.py
wapp/templates/automigrate.py
wapp/templates/env.py
wapp/templates/settings.py
wapp/templates/users_demo.py
wapp/tools/__init__.py
wapp/tools/export_openapi_ts.py
saitech_wapp-0.2.11.dist-info/METADATA
saitech_wapp-0.2.11.dist-info/WHEEL
saitech_wapp-0.2.11.dist-info/entry_points.txt
saitech_wapp-0.2.11.dist-info/top_level.txt
saitech_wapp-0.2.11.dist-info/RECORD
