Metadata-Version: 2.4
Name: saitech-wapp
Version: 0.2.11
Summary: A lightweight FastAPI helper framework with async SQLAlchemy auto-CRUD and migrations
Author: saitech
License: MIT
Project-URL: Homepage, https://github.com/saitech-org/wapp
Requires-Python: >=3.8
License-File: LICENSE
Requires-Dist: alembic
Requires-Dist: python-dotenv
Requires-Dist: fastapi
Requires-Dist: uvicorn[standard]
Requires-Dist: sqlalchemy
Requires-Dist: pydantic
Requires-Dist: aiosqlite
Dynamic: license-file
